lambada/__init__.py
lambada/cli.py
lambada/handlers.py
simiotics_lambada-0.2.0.dist-info/LICENSE
simiotics_lambada-0.2.0.dist-info/METADATA
simiotics_lambada-0.2.0.dist-info/WHEEL
simiotics_lambada-0.2.0.dist-info/entry_points.txt
simiotics_lambada-0.2.0.dist-info/top_level.txt
simiotics_lambada-0.2.0.dist-info/RECORD
