Metadata-Version: 2.1
Name: simiotics-lambada
Version: 0.2.0
Summary: Manage AWS Lambda functions using a Simiotics Function Registry
Home-page: https://github.com/simiotics/lambada
Author: Neeraj Kashyap
Author-email: neeraj@simiotics.com
License: UNKNOWN
Platform: UNKNOWN
Classifier: License :: OSI Approved :: Apache Software License
Classifier: Development Status :: 2 - Pre-Alpha
Classifier: Programming Language :: Python
Requires-Dist: boto3
Requires-Dist: simiotics
